gl_snippet/__init__.py
gl_snippet/version.py
gl_snippet-0.1.7.0.dist-info/LICENSE
gl_snippet-0.1.7.0.dist-info/METADATA
gl_snippet-0.1.7.0.dist-info/WHEEL
gl_snippet-0.1.7.0.dist-info/entry_points.txt
gl_snippet-0.1.7.0.dist-info/top_level.txt
gl_snippet-0.1.7.0.dist-info/RECORD
