Metadata-Version: 2.1
Name: gl-snippet
Version: 0.1.7.0
Summary: "Fetch snippet to local file"
Home-page: https://gitlab.com/bredbeddle-open/gl-snippet
Author: Curtis Forrester
License: MIT
Platform: UNKNOWN
Classifier: Development Status :: 5 - Production/Stable
Classifier: Environment :: Console
Classifier: Framework :: Flake8
Classifier: Intended Audience :: Developers
Classifier: License :: OSI Approved :: MIT License
Classifier: Programming Language :: Python
Classifier: Programming Language :: Python :: 2.7
Classifier: Programming Language :: Python :: 3.7
Classifier: Programming Language :: Python :: 3.9
Requires-Python: >=2.7
License-File: LICENSE
Requires-Dist: python-gitlab
Requires-Dist: click
